FiD_dialogue/LICENSE
FiD_dialogue/README.md
FiD_dialogue/__init__.py
FiD_dialogue/dialogue_agent_test.ipynb
FiD_dialogue/fidagent.py
FiD_dialogue/persona_chat_preprocess.ipynb
FiD_dialogue/reader_test.py
FiD_dialogue/reader_train.py
FiD_dialogue/requirements.txt
FiD_dialogue/src/__init__.py
FiD_dialogue/src/data.py
FiD_dialogue/src/evaluation.py
FiD_dialogue/src/model.py
FiD_dialogue/src/options.py
FiD_dialogue/src/slurm.py
FiD_dialogue/src/util.py
RAG_LLM_dialogue/ReadMe.md
RAG_LLM_dialogue/__init__.py
RAG_LLM_dialogue/chat_bot.py
RAG_LLM_dialogue/data/dialogues.tsv
RAG_LLM_dialogue/data/facts.csv
RAG_LLM_dialogue/data/profiles.tsv
RAG_LLM_dialogue/data_storage.py
RAG_LLM_dialogue/demo.py
RAG_LLM_dialogue/faiss_index/index.faiss
RAG_LLM_dialogue/faiss_index/index.pkl
RAG_LLM_dialogue/models/model-q4_K.gguf
RAG_LLM_dialogue/query_document.py
RAG_LLM_dialogue/relevant_doc.py
RAG_LLM_dialogue/requirements.txt
RAG_LLM_dialogue/src/__init__.py
RAG_LLM_dialogue/src/biencoder_test.py
RAG_LLM_dialogue/src/biencoder_train.py
RAG_LLM_dialogue/src/data_processing.ipynb
RAG_LLM_dialogue/src/model.py
RAG_emotions/__init__.py
RAG_emotions/conversaition.py
RAG_emotions/faiss_retriver_cosine.py
RAG_emotions/preprocessing.py
RAG_emotions/rag.ipynb
RAG_emotions/rag.py
RAG_emotions/ruGPT-3.5-13B-lora/README.md
RAG_emotions/ruGPT-3.5-13B-lora/__init__.py
RAG_emotions/ruGPT-3.5-13B-lora/adapter_config.json
RAG_emotions/ruGPT-3.5-13B-lora/adapter_model.bin
RAG_emotions/ruGPT-3.5-13B-lora/added_tokens.json
RAG_emotions/ruGPT-3.5-13B-lora/generation_config.json
RAG_emotions/ruGPT-3.5-13B-lora/merges.txt
RAG_emotions/ruGPT-3.5-13B-lora/special_tokens_map.json
RAG_emotions/ruGPT-3.5-13B-lora/tokenizer_config.json
RAG_emotions/ruGPT-3.5-13B-lora/vocab.json
augmentation/__init__.py
augmentation/emotion_augmentation.py
emotion_recognition/__init__.py
emotion_recognition/emotions/__init__.py
emotion_recognition/emotions/config.yml
emotion_recognition/emotions/lightning_data_module.py
rupersonaagent-0.2.0.dist-info/LICENSE
rupersonaagent-0.2.0.dist-info/METADATA
rupersonaagent-0.2.0.dist-info/WHEEL
rupersonaagent-0.2.0.dist-info/RECORD
