Metadata-Version: 2.1
Name: rupersonaagent
Version: 0.2.0
Summary: library for creating a Russian-language dialog assistant
Home-page: https://gitlab.com/Iolly/rupersonaagent
License: MIT
Author: Your Name
Author-email: you@example.com
Requires-Python: ==3.11.4
Classifier: License :: OSI Approved :: MIT License
Classifier: Programming Language :: Python :: 3
Project-URL: Repository, https://gitlab.com/Iolly/rupersonaagent
